AUTHORS.rst
COPYRIGHT
HISTORY.rst
LICENSE
MANIFEST.in
README.rst
setup.cfg
setup.py
docs/authors.rst
docs/history.rst
docs/index.rst
docs/installation.rst
docs/readme.rst
docs/usage.rst
docs/reference/index.rst
docs/testing/availabletests.rst
docs/testing/howto.rst
docs/testing/index.rst
test_app/__init__.py
test_app/apps.py
test_app/forms.py
test_app/models.py
test_app/settings.py
thecut/__init__.py
thecut/emailfield/__init__.py
thecut/emailfield/apps.py
thecut/emailfield/forms.py
thecut/emailfield/models.py
thecut/emailfield/validators.py
thecut/emailfield/tests/__init__.py
thecut/emailfield/tests/test_forms.py
thecut/emailfield/tests/test_models.py
thecut_emailfield.egg-info/PKG-INFO
thecut_emailfield.egg-info/SOURCES.txt
thecut_emailfield.egg-info/dependency_links.txt
thecut_emailfield.egg-info/namespace_packages.txt
thecut_emailfield.egg-info/requires.txt
thecut_emailfield.egg-info/top_level.txt