Metadata-Version: 1.1
Name: thecut-emailfield
Version: 1.0.2
Summary: A Django email field which validates by checking for an MX record on the domain.
Home-page: https://projects.thecut.net.au/projects/thecut-emailfield
Author: The Cut
Author-email: development@thecut.net.au
License: Apache Software License 2.0
Platform: any
Classifier: Programming Language :: Python
Classifier: Development Status :: 4 - Beta
Classifier: Natural Language :: English
Classifier: Environment :: Web Environment
Classifier: Intended Audience :: Developers
Classifier: License :: OSI Approved :: Apache Software License
Classifier: Operating System :: OS Independent
Classifier: Topic :: Software Development :: Libraries :: Python Modules
Classifier: Topic :: Software Development :: Libraries :: Application Frameworks
Classifier: Topic :: Internet :: WWW/HTTP :: Dynamic Content
Classifier: Framework :: Django
Classifier: Framework :: Django :: 1.8
Classifier: Framework :: Django :: 1.9
Classifier: Framework :: Django :: 1.10
